{"cod": "200", "message": 0, "cnt": 40, "list": [{"dt": 1707447600, "main": {"temp": -18.72, "feels_like": -24.07, "temp_min": -18.72, "temp_max": -17.75, "pressure": 1007, "sea_level": 1007, "grnd_level": 1004, "humidity": 95, "temp_kf": -0.97}, "weather": [{"id": 802, "main": "Clouds", "description": "scattered clouds", "icon": "03n"}], "clouds": {"all": 27}, "wind": {"speed": 1.91, "deg": 5, "gust": 2.09}, "visibility": 10000, "pop": 0, "sys": {"pod": "n"}, "dt_txt": "2024-02-09 03:00:00"}, {"dt": 1707458400, "main": {"temp": -18.67, "feels_like": -23.93, "temp_min": -18.67, "temp_max": -18.57, "pressure": 1008, "sea_level": 1008, "grnd_level": 1005, "humidity": 94, "temp_kf": -0.1}, "weather": [{"id": 802, "main": "Clouds", "description": "scattered clouds", "icon": "03n"}], "clouds": {"all": 26}, "wind": {"speed": 1.87, "deg": 7, "gust": 2.03}, "visibility": 10000, "pop": 0, "sys": {"pod": "n"}, "dt_txt": "2024-02-09 06:00:00"}, {"dt": 1707469200, "main": {"temp": -15.81, "feels_like": -20.36, "temp_min": -15.81, "temp_max": -14.36, "pressure": 1008, "sea_level": 1008, "grnd_level": 1006, "humidity": 89, "temp_kf": -1.45}, "weather": [{"id": 801, "main": "Clouds", "description": "few clouds", "icon": "02d"}], "clouds": {"all": 20}, "wind": {"speed": 1.75, "deg": 17, "gust": 2.43}, "visibility": 10000, "pop": 0, "sys": {"pod": "d"}, "dt_txt": "2024-02-09 09:00:00"}, {"dt": 1707480000, "main": {"temp": -9, "feels_like": -12.26, "temp_min": -9, "temp_max": -9, "pressure": 1008, "sea_level": 1008, "grnd_level": 1005, "humidity": 78, "temp_kf": 0}, "weather": [{"id": 801, "main": "Clouds", "description": "few clouds", "icon": "02d"}], "clouds": {"all": 14}, "wind": {"speed": 1.62, "deg": 33, "gust": 2.63}, "visibility": 10000, "pop": 0, "sys": {"pod": "d"}, "dt_txt": "2024-02-09 12:00:00"}, {"dt": 1707490800, "main": {"temp": -10.39, "feels_like": -14.31, "temp_min": -10.39, "temp_max": -10.39, "pressure": 1008, "sea_level": 1008, "grnd_level": 1005, "humidity": 89, "temp_kf": 0}, "weather": [{"id": 801, "main": "Clouds", "description": "few clouds", "icon": "02d"}], "clouds": {"all": 21}, "wind": {"speed": 1.86, "deg": 28, "gust": 3.03}, "visibility": 10000, "pop": 0, "sys": {"pod": "d"}, "dt_txt": "2024-02-09 15:00:00"}, {"dt": 1707501600, "main": {"temp": -13.97, "feels_like": -19.45, "temp_min": -13.97, "temp_max": -13.97, "pressure": 1009, "sea_level": 1009, "grnd_level": 1006, "humidity": 91, "temp_kf": 0}, "weather": [{"id": 803, "main": "Clouds", "description": "broken clouds", "icon": "04n"}], "clouds": {"all": 57}, "wind": {"speed": 2.42, "deg": 6, "gust": 4.44}, "visibility": 10000, "pop": 0, "sys": {"pod": "n"}, "dt_txt": "2024-02-09 18:00:00"}, {"dt": 1707512400, "main": {"temp": -12.26, "feels_like": -17.38, "temp_min": -12.26, "temp_max": -12.26, "pressure": 1009, "sea_level": 1009, "grnd_level": 1006, "humidity": 94, "temp_kf": 0}, "weather": [{"id": 804, "main": "Clouds", "description": "overcast clouds", "icon": "04n"}], "clouds": {"all": 100}, "wind": {"speed": 2.39, "deg": 16, "gust": 4.76}, "visibility": 358, "pop": 0, "sys": {"pod": "n"}, "dt_txt": "2024-02-09 21:00:00"}, {"dt": 1707523200, "main": {"temp": -11.19, "feels_like": -16.01, "temp_min": -11.19, "temp_max": -11.19, "pressure": 1010, "sea_level": 1010, "grnd_level": 1006, "humidity": 94, "temp_kf": 0}, "weather": [{"id": 600, "main": "Snow", "description": "light snow", "icon": "13n"}], "clouds": {"all": 100}, "wind": {"speed": 2.32, "deg": 19, "gust": 5.4}, "visibility": 6340, "pop": 0.28, "snow": {"3h": 0.21}, "sys": {"pod": "n"}, "dt_txt": "2024-02-10 00:00:00"}, {"dt": 1707534000, "main": {"temp": -12.05, "feels_like": -17.51, "temp_min": -12.05, "temp_max": -12.05, "pressure": 1009, "sea_level": 1009, "grnd_level": 1006, "humidity": 93, "temp_kf": 0}, "weather": [{"id": 804, "main": "Clouds", "description": "overcast clouds", "icon": "04n"}], "clouds": {"all": 100}, "wind": {"speed": 2.65, "deg": 16, "gust": 6.58}, "visibility": 10000, "pop": 0, "sys": {"pod": "n"}, "dt_txt": "2024-02-10 03:00:00"}, {"dt": 1707544800, "main": {"temp": -11.51, "feels_like": -17.08, "temp_min": -11.51, "temp_max": -11.51, "pressure": 1010, "sea_level": 1010, "grnd_level": 1006, "humidity": 89, "temp_kf": 0}, "weather": [{"id": 804, "main": "Clouds", "description": "overcast clouds", "icon": "04n"}], "clouds": {"all": 100}, "wind": {"speed": 2.81, "deg": 18, "gust": 7.48}, "visibility": 10000, "pop": 0, "sys": {"pod": "n"}, "dt_txt": "2024-02-10 06:00:00"}, {"dt": 1707555600, "main": {"temp": -9.89, "feels_like": -15.49, "temp_min": -9.89, "temp_max": -9.89, "pressure": 1010, "sea_level": 1010, "grnd_level": 1007, "humidity": 85, "temp_kf": 0}, "weather": [{"id": 804, "main": "Clouds", "description": "overcast clouds", "icon": "04d"}], "clouds": {"all": 100}, "wind": {"speed": 3.09, "deg": 22, "gust": 8.92}, "visibility": 10000, "pop": 0, "sys": {"pod": "d"}, "dt_txt": "2024-02-10 09:00:00"}, {"dt": 1707566400, "main": {"temp": -7.91, "feels_like": -13.38, "temp_min": -7.91, "temp_max": -7.91, "pressure": 1009, "sea_level": 1009, "grnd_level": 1006, "humidity": 82, "temp_kf": 0}, "weather": [{"id": 804, "main": "Clouds", "description": "overcast clouds", "icon": "04d"}], "clouds": {"all": 100}, "wind": {"speed": 3.35, "deg": 32, "gust": 6.71}, "visibility": 10000, "pop": 0, "sys": {"pod": "d"}, "dt_txt": "2024-02-10 12:00:00"}, {"dt": 1707577200, "main": {"temp": -8.16, "feels_like": -13.55, "temp_min": -8.16, "temp_max": -8.16, "pressure": 1009, "sea_level": 1009, "grnd_level": 1006, "humidity": 88, "temp_kf": 0}, "weather": [{"id": 804, "main": "Clouds", "description": "overcast clouds", "icon": "04d"}], "clouds": {"all": 100}, "wind": {"speed": 3.22, "deg": 23, "gust": 8.52}, "visibility": 3823, "pop": 0.12, "sys": {"pod": "d"}, "dt_txt": "2024-02-10 15:00:00"}, {"dt": 1707588000, "main": {"temp": -8.52, "feels_like": -13.78, "temp_min": -8.52, "temp_max": -8.52, "pressure": 1009, "sea_level": 1009, "grnd_level": 1006, "humidity": 92, "temp_kf": 0}, "weather": [{"id": 600, "main": "Snow", "description": "light snow", "icon": "13n"}], "clouds": {"all": 100}, "wind": {"speed": 3.04, "deg": 11, "gust": 8.21}, "visibility": 328, "pop": 0.22, "snow": {"3h": 0.3}, "sys": {"pod": "n"}, "dt_txt": "2024-02-10 18:00:00"}, {"dt": 1707598800, "main": {"temp": -8.18, "feels_like": -12.99, "temp_min": -8.18, "temp_max": -8.18, "pressure": 1009, "sea_level": 1009, "grnd_level": 1006, "humidity": 93, "temp_kf": 0}, "weather": [{"id": 600, "main": "Snow", "description": "light snow", "icon": "13n"}], "clouds": {"all": 100}, "wind": {"speed": 2.72, "deg": 4, "gust": 6.36}, "visibility": 276, "pop": 0.84, "snow": {"3h": 0.71}, "sys": {"pod": "n"}, "dt_txt": "2024-02-10 21:00:00"}, {"dt": 1707609600, "main": {"temp": -7.89, "feels_like": -12.29, "temp_min": -7.89, "temp_max": -7.89, "pressure": 1009, "sea_level": 1009, "grnd_level": 1006, "humidity": 94, "temp_kf": 0}, "weather": [{"id": 600, "main": "Snow", "description": "light snow", "icon": "13n"}], "clouds": {"all": 100}, "wind": {"speed": 2.44, "deg": 6, "gust": 5.64}, "visibility": 266, "pop": 0.8, "snow": {"3h": 0.48}, "sys": {"pod": "n"}, "dt_txt": "2024-02-11 00:00:00"}, {"dt": 1707620400, "main": {"temp": -7.34, "feels_like": -11.31, "temp_min": -7.34, "temp_max": -7.34, "pressure": 1009, "sea_level": 1009, "grnd_level": 1006, "humidity": 95, "temp_kf": 0}, "weather": [{"id": 600, "main": "Snow", "description": "light snow", "icon": "13n"}], "clouds": {"all": 100}, "wind": {"speed": 2.2, "deg": 8, "gust": 5.35}, "visibility": 164, "pop": 0.72, "snow": {"3h": 0.85}, "sys": {"pod": "n"}, "dt_txt": "2024-02-11 03:00:00"}, {"dt": 1707631200, "main": {"temp": -7.76, "feels_like": -11.81, "temp_min": -7.76, "temp_max": -7.76, "pressure": 1009, "sea_level": 1009, "grnd_level": 1006, "humidity": 94, "temp_kf": 0}, "weather": [{"id": 600, "main": "Snow", "description": "light snow", "icon": "13n"}], "clouds": {"all": 99}, "wind": {"speed": 2.21, "deg": 9, "gust": 5.1}, "visibility": 495, "pop": 0.75, "snow": {"3h": 0.35}, "sys": {"pod": "n"}, "dt_txt": "2024-02-11 06:00:00"}, {"dt": 1707642000, "main": {"temp": -6.55, "feels_like": -10.76, "temp_min": -6.55, "temp_max": -6.55, "pressure": 1010, "sea_level": 1010, "grnd_level": 1006, "humidity": 91, "temp_kf": 0}, "weather": [{"id": 600, "main": "Snow", "description": "light snow", "icon": "13d"}], "clouds": {"all": 100}, "wind": {"speed": 2.48, "deg": 15, "gust": 5.48}, "visibility": 842, "pop": 0.37, "snow": {"3h": 0.19}, "sys": {"pod": "d"}, "dt_txt": "2024-02-11 09:00:00"}, {"dt": 1707652800, "main": {"temp": -4.51, "feels_like": -8.74, "temp_min": -4.51, "temp_max": -4.51, "pressure": 1009, "sea_level": 1009, "grnd_level": 1006, "humidity": 86, "temp_kf": 0}, "weather": [{"id": 600, "main": "Snow", "description": "light snow", "icon": "13d"}], "clouds": {"all": 100}, "wind": {"speed": 2.83, "deg": 25, "gust": 5.11}, "visibility": 3019, "pop": 0.25, "snow": {"3h": 0.13}, "sys": {"pod": "d"}, "dt_txt": "2024-02-11 12:00:00"}, {"dt": 1707663600, "main": {"temp": -4.8, "feels_like": -9.47, "temp_min": -4.8, "temp_max": -4.8, "pressure": 1009, "sea_level": 1009, "grnd_level": 1006, "humidity": 89, "temp_kf": 0}, "weather": [{"id": 804, "main": "Clouds", "description": "overcast clouds", "icon": "04d"}], "clouds": {"all": 100}, "wind": {"speed": 3.2, "deg": 25, "gust": 8.16}, "visibility": 4783, "pop": 0.03, "sys": {"pod": "d"}, "dt_txt": "2024-02-11 15:00:00"}, {"dt": 1707674400, "main": {"temp": -5.35, "feels_like": -10.25, "temp_min": -5.35, "temp_max": -5.35, "pressure": 1010, "sea_level": 1010, "grnd_level": 1006, "humidity": 92, "temp_kf": 0}, "weather": [{"id": 600, "main": "Snow", "description": "light snow", "icon": "13n"}], "clouds": {"all": 100}, "wind": {"speed": 3.32, "deg": 16, "gust": 9.37}, "visibility": 450, "pop": 0.39, "snow": {"3h": 0.21}, "sys": {"pod": "n"}, "dt_txt": "2024-02-11 18:00:00"}, {"dt": 1707685200, "main": {"temp": -5.17, "feels_like": -10.14, "temp_min": -5.17, "temp_max": -5.17, "pressure": 1009, "sea_level": 1009, "grnd_level": 1006, "humidity": 94, "temp_kf": 0}, "weather": [{"id": 600, "main": "Snow", "description": "light snow", "icon": "13n"}], "clouds": {"all": 100}, "wind": {"speed": 3.43, "deg": 17, "gust": 9.24}, "visibility": 213, "pop": 0.71, "snow": {"3h": 0.54}, "sys": {"pod": "n"}, "dt_txt": "2024-02-11 21:00:00"}, {"dt": 1707696000, "main": {"temp": -5.51, "feels_like": -10.7, "temp_min": -5.51, "temp_max": -5.51, "pressure": 1009, "sea_level": 1009, "grnd_level": 1006, "humidity": 94, "temp_kf": 0}, "weather": [{"id": 600, "main": "Snow", "description": "light snow", "icon": "13n"}], "clouds": {"all": 100}, "wind": {"speed": 3.59, "deg": 18, "gust": 9.54}, "visibility": 167, "pop": 0.87, "snow": {"3h": 1.11}, "sys": {"pod": "n"}, "dt_txt": "2024-02-12 00:00:00"}, {"dt": 1707706800, "main": {"temp": -5.94, "feels_like": -11.68, "temp_min": -5.94, "temp_max": -5.94, "pressure": 1008, "sea_level": 1008, "grnd_level": 1005, "humidity": 93, "temp_kf": 0}, "weather": [{"id": 600, "main": "Snow", "description": "light snow", "icon": "13n"}], "clouds": {"all": 100}, "wind": {"speed": 4.12, "deg": 21, "gust": 10.91}, "visibility": 204, "pop": 0.99, "snow": {"3h": 1.21}, "sys": {"pod": "n"}, "dt_txt": "2024-02-12 03:00:00"}, {"dt": 1707717600, "main": {"temp": -6, "feels_like": -11.75, "temp_min": -6, "temp_max": -6, "pressure": 1008, "sea_level": 1008, "grnd_level": 1005, "humidity": 93, "temp_kf": 0}, "weather": [{"id": 600, "main": "Snow", "description": "light snow", "icon": "13n"}], "clouds": {"all": 100}, "wind": {"speed": 4.12, "deg": 20, "gust": 10.97}, "visibility": 176, "pop": 0.95, "snow": {"3h": 1.01}, "sys": {"pod": "n"}, "dt_txt": "2024-02-12 06:00:00"}, {"dt": 1707728400, "main": {"temp": -5.57, "feels_like": -11.12, "temp_min": -5.57, "temp_max": -5.57, "pressure": 1008, "sea_level": 1008, "grnd_level": 1005, "humidity": 93, "temp_kf": 0}, "weather": [{"id": 600, "main": "Snow", "description": "light snow", "icon": "13d"}], "clouds": {"all": 100}, "wind": {"speed": 3.99, "deg": 19, "gust": 10.56}, "visibility": 154, "pop": 0.95, "snow": {"3h": 1.17}, "sys": {"pod": "d"}, "dt_txt": "2024-02-12 09:00:00"}, {"dt": 1707739200, "main": {"temp": -4.5, "feels_like": -10.26, "temp_min": -4.5, "temp_max": -4.5, "pressure": 1007, "sea_level": 1007, "grnd_level": 1004, "humidity": 93, "temp_kf": 0}, "weather": [{"id": 601, "main": "Snow", "description": "snow", "icon": "13d"}], "clouds": {"all": 100}, "wind": {"speed": 4.59, "deg": 20, "gust": 11.23}, "visibility": 159, "pop": 1, "snow": {"3h": 1.91}, "sys": {"pod": "d"}, "dt_txt": "2024-02-12 12:00:00"}, {"dt": 1707750000, "main": {"temp": -3.96, "feels_like": -9.47, "temp_min": -3.96, "temp_max": -3.96, "pressure": 1007, "sea_level": 1007, "grnd_level": 1004, "humidity": 94, "temp_kf": 0}, "weather": [{"id": 601, "main": "Snow", "description": "snow", "icon": "13d"}], "clouds": {"all": 100}, "wind": {"speed": 4.42, "deg": 23, "gust": 10.95}, "visibility": 157, "pop": 1, "snow": {"3h": 4.28}, "sys": {"pod": "d"}, "dt_txt": "2024-02-12 15:00:00"}, {"dt": 1707760800, "main": {"temp": -3.57, "feels_like": -9.08, "temp_min": -3.57, "temp_max": -3.57, "pressure": 1007, "sea_level": 1007, "grnd_level": 1004, "humidity": 95, "temp_kf": 0}, "weather": [{"id": 601, "main": "Snow", "description": "snow", "icon": "13n"}], "clouds": {"all": 100}, "wind": {"speed": 4.56, "deg": 35, "gust": 11.08}, "visibility": 151, "pop": 1, "snow": {"3h": 4.38}, "sys": {"pod": "n"}, "dt_txt": "2024-02-12 18:00:00"}, {"dt": 1707771600, "main": {"temp": -3.89, "feels_like": -8.73, "temp_min": -3.89, "temp_max": -3.89, "pressure": 1008, "sea_level": 1008, "grnd_level": 1004, "humidity": 95, "temp_kf": 0}, "weather": [{"id": 601, "main": "Snow", "description": "snow", "icon": "13n"}], "clouds": {"all": 100}, "wind": {"speed": 3.6, "deg": 32, "gust": 9.79}, "visibility": 139, "pop": 1, "snow": {"3h": 3.46}, "sys": {"pod": "n"}, "dt_txt": "2024-02-12 21:00:00"}, {"dt": 1707782400, "main": {"temp": -4.6, "feels_like": -9.1, "temp_min": -4.6, "temp_max": -4.6, "pressure": 1008, "sea_level": 1008, "grnd_level": 1005, "humidity": 95, "temp_kf": 0}, "weather": [{"id": 601, "main": "Snow", "description": "snow", "icon": "13n"}], "clouds": {"all": 100}, "wind": {"speed": 3.07, "deg": 18, "gust": 8.61}, "visibility": 157, "pop": 1, "snow": {"3h": 2.38}, "sys": {"pod": "n"}, "dt_txt": "2024-02-13 00:00:00"}, {"dt": 1707793200, "main": {"temp": -4.92, "feels_like": -8.75, "temp_min": -4.92, "temp_max": -4.92, "pressure": 1008, "sea_level": 1008, "grnd_level": 1005, "humidity": 95, "temp_kf": 0}, "weather": [{"id": 600, "main": "Snow", "description": "light snow", "icon": "13n"}], "clouds": {"all": 100}, "wind": {"speed": 2.42, "deg": 356, "gust": 6.49}, "visibility": 403, "pop": 0.99, "snow": {"3h": 1.2}, "sys": {"pod": "n"}, "dt_txt": "2024-02-13 03:00:00"}, {"dt": 1707804000, "main": {"temp": -8.78, "feels_like": -12.67, "temp_min": -8.78, "temp_max": -8.78, "pressure": 1008, "sea_level": 1008, "grnd_level": 1005, "humidity": 96, "temp_kf": 0}, "weather": [{"id": 600, "main": "Snow", "description": "light snow", "icon": "13n"}], "clouds": {"all": 95}, "wind": {"speed": 1.99, "deg": 349, "gust": 4.08}, "visibility": 9528, "pop": 0.85, "snow": {"3h": 0.1}, "sys": {"pod": "n"}, "dt_txt": "2024-02-13 06:00:00"}, {"dt": 1707814800, "main": {"temp": -6.85, "feels_like": -10.2, "temp_min": -6.85, "temp_max": -6.85, "pressure": 1009, "sea_level": 1009, "grnd_level": 1006, "humidity": 93, "temp_kf": 0}, "weather": [{"id": 804, "main": "Clouds", "description": "overcast clouds", "icon": "04d"}], "clouds": {"all": 88}, "wind": {"speed": 1.85, "deg": 358, "gust": 3.91}, "visibility": 10000, "pop": 0, "sys": {"pod": "d"}, "dt_txt": "2024-02-13 09:00:00"}, {"dt": 1707825600, "main": {"temp": -3.28, "feels_like": -6.58, "temp_min": -3.28, "temp_max": -3.28, "pressure": 1009, "sea_level": 1009, "grnd_level": 1006, "humidity": 87, "temp_kf": 0}, "weather": [{"id": 804, "main": "Clouds", "description": "overcast clouds", "icon": "04d"}], "clouds": {"all": 86}, "wind": {"speed": 2.23, "deg": 24, "gust": 4.24}, "visibility": 10000, "pop": 0, "sys": {"pod": "d"}, "dt_txt": "2024-02-13 12:00:00"}, {"dt": 1707836400, "main": {"temp": -4.18, "feels_like": -8.06, "temp_min": -4.18, "temp_max": -4.18, "pressure": 1009, "sea_level": 1009, "grnd_level": 1006, "humidity": 92, "temp_kf": 0}, "weather": [{"id": 804, "main": "Clouds", "description": "overcast clouds", "icon": "04d"}], "clouds": {"all": 100}, "wind": {"speed": 2.57, "deg": 27, "gust": 4.93}, "visibility": 6629, "pop": 0, "sys": {"pod": "d"}, "dt_txt": "2024-02-13 15:00:00"}, {"dt": 1707847200, "main": {"temp": -4.88, "feels_like": -9.67, "temp_min": -4.88, "temp_max": -4.88, "pressure": 1009, "sea_level": 1009, "grnd_level": 1006, "humidity": 92, "temp_kf": 0}, "weather": [{"id": 600, "main": "Snow", "description": "light snow", "icon": "13n"}], "clouds": {"all": 100}, "wind": {"speed": 3.31, "deg": 10, "gust": 9.82}, "visibility": 2365, "pop": 0.23, "snow": {"3h": 0.13}, "sys": {"pod": "n"}, "dt_txt": "2024-02-13 18:00:00"}, {"dt": 1707858000, "main": {"temp": -3.72, "feels_like": -8.6, "temp_min": -3.72, "temp_max": -3.72, "pressure": 1009, "sea_level": 1009, "grnd_level": 1005, "humidity": 95, "temp_kf": 0}, "weather": [{"id": 601, "main": "Snow", "description": "snow", "icon": "13n"}], "clouds": {"all": 100}, "wind": {"speed": 3.69, "deg": 11, "gust": 10.49}, "visibility": 139, "pop": 0.92, "snow": {"3h": 2.27}, "sys": {"pod": "n"}, "dt_txt": "2024-02-13 21:00:00"}, {"dt": 1707868800, "main": {"temp": -4.21, "feels_like": -8.88, "temp_min": -4.21, "temp_max": -4.21, "pressure": 1009, "sea_level": 1009, "grnd_level": 1005, "humidity": 95, "temp_kf": 0}, "weather": [{"id": 601, "main": "Snow", "description": "snow", "icon": "13n"}], "clouds": {"all": 100}, "wind": {"speed": 3.33, "deg": 9, "gust": 9.54}, "visibility": 137, "pop": 1, "snow": {"3h": 2.76}, "sys": {"pod": "n"}, "dt_txt": "2024-02-14 00:00:00"}], "city": {"id": 3143244, "name": "Oslo", "coord": {"lat": 59.9127, "lon": 10.7461}, "country": "NO", "population": 580000, "timezone": 3600, "sunrise": 1707462758, "sunset": 1707493792}}